congressional_trades/__init__.py
congressional_trades/cache.py
congressional_trades/cli.py
congressional_trades/models.py
congressional_trades/ticker_resolver.py
congressional_trades/parsers/__init__.py
congressional_trades/scrapers/__init__.py
congressional_trades/scrapers/fallback.py
congressional_trades/scrapers/senate.py
congressional_trades-0.1.0.dist-info/METADATA
congressional_trades-0.1.0.dist-info/WHEEL
congressional_trades-0.1.0.dist-info/entry_points.txt
congressional_trades-0.1.0.dist-info/RECORD
