Metadata-Version: 2.4
Name: congressional-trades
Version: 0.1.0
Summary: Scrape and analyze stock trades by members of US Congress
Project-URL: Homepage, https://github.com/guttu44/congressional-trades
Project-URL: Repository, https://github.com/guttu44/congressional-trades
Project-URL: Issues, https://github.com/guttu44/congressional-trades/issues
Author: Mathias Guttu
License-Expression: MIT
Keywords: congress,finance,house,politics,senate,stocks,trading
Classifier: Development Status :: 3 - Alpha
Classifier: Intended Audience :: Developers
Classifier: Intended Audience :: Financial and Insurance Industry
Classifier: License :: OSI Approved :: MIT License
Classifier: Programming Language :: Python :: 3
Classifier: Programming Language :: Python :: 3.10
Classifier: Programming Language :: Python :: 3.11
Classifier: Programming Language :: Python :: 3.12
Classifier: Topic :: Office/Business :: Financial :: Investment
Requires-Python: >=3.10
Requires-Dist: httpx>=0.25.0
Requires-Dist: pandas>=2.0.0
Requires-Dist: pydantic>=2.0.0
Requires-Dist: selectolax>=0.3.0
Provides-Extra: dev
Requires-Dist: pytest-asyncio>=0.21.0; extra == 'dev'
Requires-Dist: pytest>=7.0.0; extra == 'dev'
Requires-Dist: ruff>=0.1.0; extra == 'dev'
Provides-Extra: scrape
Requires-Dist: pdfplumber>=0.10.0; extra == 'scrape'
